poly2pascal/__init__.py
poly2pascal/annotations.py
poly2pascal/data_loader.py
poly2pascal-0.0.5.dist-info/LICENSE
poly2pascal-0.0.5.dist-info/METADATA
poly2pascal-0.0.5.dist-info/WHEEL
poly2pascal-0.0.5.dist-info/top_level.txt
poly2pascal-0.0.5.dist-info/RECORD
