Metadata-Version: 2.1
Name: poly2pascal
Version: 0.0.5
Summary: Convert POLYGON bounding boxes from .csv files to .xml annotation files in the Pascal VOC format for computer vision projects.
Home-page: https://github.com/ruankie/poly2pascal
Author: Ruan Pretorius
Project-URL: Documentation, https://ruankie.github.io/poly2pascal/
Project-URL: Source Code, https://github.com/ruankie/poly2pascal
Project-URL: Bug Tracker, https://github.com/ruankie/poly2pascal/issues
Classifier: Programming Language :: Python :: 3
Classifier: License :: OSI Approved :: MIT License
Classifier: Operating System :: OS Independent
License-File: LICENSE
Requires-Dist: opencv-python (>=4)
Requires-Dist: geopandas (>=0.10)
Provides-Extra: dev
Requires-Dist: pytest (>=7) ; extra == 'dev'
Requires-Dist: coverage (>=6) ; extra == 'dev'
Requires-Dist: black (>=22) ; extra == 'dev'
Requires-Dist: pylint (>=2) ; extra == 'dev'
Requires-Dist: jupyterlab (>=3) ; extra == 'dev'
Requires-Dist: sphinx (>=5) ; extra == 'dev'
Requires-Dist: sphinx-rtd-theme (>=1) ; extra == 'dev'
